gr_tk/__init__.py
gr_tk/be.py
gr_tk/em.py
gr_tk/gr.py
gr_tk/po.py
gr_tk/ta.py
gr_tk-0.1.0.dist-info/entry_points.txt
gr_tk-0.1.0.dist-info/LICENSE
gr_tk-0.1.0.dist-info/METADATA
gr_tk-0.1.0.dist-info/WHEEL
gr_tk-0.1.0.dist-info/RECORD
